featuretoggles/__init__.py
tests/__init__.py
tests/test_featuretoggles.py
featuretoggles-1.0.2.dist-info/LICENSE
featuretoggles-1.0.2.dist-info/METADATA
featuretoggles-1.0.2.dist-info/WHEEL
featuretoggles-1.0.2.dist-info/top_level.txt
featuretoggles-1.0.2.dist-info/RECORD
