Metadata-Version: 2.1
Name: featuretoggles
Version: 1.0.2
Summary: A package to configure feature flags and log the use of the toggles
Home-page: https://github.com/vwt-digital/feature-toggles
Author: VWT Digital
Author-email: support@vwt.digital
License: GPLv3+
Platform: UNKNOWN
Classifier: Programming Language :: Python :: 3.7
Classifier: License :: OSI Approved :: GNU General Public License v3 or later (GPLv3+)
Classifier: Operating System :: OS Independent
Classifier: Intended Audience :: Developers
Classifier: Natural Language :: English
Classifier: Topic :: Software Development :: Libraries :: Python Modules
Requires-Python: >=3.7
Requires-Dist: pyyaml (==5.4.1)
